betterlogging/__init__.py
betterlogging/colorized.py
betterlogging/colors.py
betterlogging/trace.py
betterlogging/version.py
betterlogging/outer/__init__.py
betterlogging/outer/better_exceptions.py
betterlogging-0.2.0.dist-info/LICENSE
betterlogging-0.2.0.dist-info/METADATA
betterlogging-0.2.0.dist-info/WHEEL
betterlogging-0.2.0.dist-info/top_level.txt
betterlogging-0.2.0.dist-info/RECORD
